identipy.py
identipy-0.0.1.dist-info/LICENSE
identipy-0.0.1.dist-info/METADATA
identipy-0.0.1.dist-info/WHEEL
identipy-0.0.1.dist-info/top_level.txt
identipy-0.0.1.dist-info/RECORD
