Metadata-Version: 2.1
Name: identipy
Version: 0.0.1
Summary: Python identity library
Home-page: UNKNOWN
Author: Marcel van den Dungen
License: UNKNOWN
Platform: UNKNOWN
Classifier: Programming Language :: Python :: 3
Classifier: Programming Language :: Python :: 3.6
Classifier: Programming Language :: Python :: 3.7
Classifier: Programming Language :: Python :: 3.8
Classifier: License :: OSI Approved :: MIT License
Classifier: Operating System :: OS Independent
Requires-Python: >=3.6
